<annotation>
	<folder>unchecked_stock_imgs</folder>
	<filename>Screenshot 2025-06-28 at 4.41.27 PM.png</filename>
	<path>/Users/koshabbas/Desktop/unchecked_stock_imgs/Screenshot 2025-06-28 at 4.41.27 PM.png</path>
	<source>
		<database>Unknown</database>
	</source>
	<size>
		<width>3166</width>
		<height>1874</height>
		<depth>3</depth>
	</size>
	<segmented>0</segmented>
	<object>
		<name>candle</name>
		<pose>Unspecified</pose>
		<truncated>0</truncated>
		<difficult>0</difficult>
		<bndbox>
			<xmin>206</xmin>
			<ymin>96</ymin>
			<xmax>232</xmax>
			<ymax>786</ymax>
		</bndbox>
	</object>
	<object>
		<name>candle</name>
		<pose>Unspecified</pose>
		<truncated>0</truncated>
		<difficult>0</difficult>
		<bndbox>
			<xmin>484</xmin>
			<ymin>536</ymin>
			<xmax>508</xmax>
			<ymax>1210</ymax>
		</bndbox>
	</object>
	<object>
		<name>candle</name>
		<pose>Unspecified</pose>
		<truncated>0</truncated>
		<difficult>0</difficult>
		<bndbox>
			<xmin>584</xmin>
			<ymin>378</ymin>
			<xmax>608</xmax>
			<ymax>1074</ymax>
		</bndbox>
	</object>
	<object>
		<name>candle</name>
		<pose>Unspecified</pose>
		<truncated>0</truncated>
		<difficult>0</difficult>
		<bndbox>
			<xmin>984</xmin>
			<ymin>1008</ymin>
			<xmax>1008</xmax>
			<ymax>1692</ymax>
		</bndbox>
	</object>
	<object>
		<name>candle</name>
		<pose>Unspecified</pose>
		<truncated>0</truncated>
		<difficult>0</difficult>
		<bndbox>
			<xmin>1196</xmin>
			<ymin>688</ymin>
			<xmax>1220</xmax>
			<ymax>1376</ymax>
		</bndbox>
	</object>
	<object>
		<name>candle</name>
		<pose>Unspecified</pose>
		<truncated>0</truncated>
		<difficult>0</difficult>
		<bndbox>
			<xmin>1700</xmin>
			<ymin>1252</ymin>
			<xmax>1722</xmax>
			<ymax>1668</ymax>
		</bndbox>
	</object>
	<object>
		<name>candle</name>
		<pose>Unspecified</pose>
		<truncated>0</truncated>
		<difficult>0</difficult>
		<bndbox>
			<xmin>2012</xmin>
			<ymin>730</ymin>
			<xmax>2032</xmax>
			<ymax>1136</ymax>
		</bndbox>
	</object>
	<object>
		<name>candle</name>
		<pose>Unspecified</pose>
		<truncated>0</truncated>
		<difficult>0</difficult>
		<bndbox>
			<xmin>2144</xmin>
			<ymin>936</ymin>
			<xmax>2160</xmax>
			<ymax>1338</ymax>
		</bndbox>
	</object>
	<object>
		<name>candle</name>
		<pose>Unspecified</pose>
		<truncated>0</truncated>
		<difficult>0</difficult>
		<bndbox>
			<xmin>2412</xmin>
			<ymin>462</ymin>
			<xmax>2430</xmax>
			<ymax>902</ymax>
		</bndbox>
	</object>
	<object>
		<name>candle</name>
		<pose>Unspecified</pose>
		<truncated>0</truncated>
		<difficult>0</difficult>
		<bndbox>
			<xmin>2810</xmin>
			<ymin>1178</ymin>
			<xmax>2824</xmax>
			<ymax>1586</ymax>
		</bndbox>
	</object>
</annotation>
